LICENSE
MANIFEST.in
README.md
pyproject.toml
requirements.txt
setup.py
smai/__init__.py
smai/cli.py
smai/core/__init__.py
smai/core/audio.py
smai/core/config.py
smai/core/conversation.py
smai/core/db.py
smai/core/default_config.py
smai/core/image.py
smai/core/inputs.py
smai/core/keys.py
smai/core/tools.py
smallish_ai.egg-info/PKG-INFO
smallish_ai.egg-info/SOURCES.txt
smallish_ai.egg-info/dependency_links.txt
smallish_ai.egg-info/entry_points.txt
smallish_ai.egg-info/requires.txt
smallish_ai.egg-info/top_level.txt