Metadata-Version: 2.4
Name: smallish-ai
Version: 0.1.0
Summary: CLI tool for multimodal AI model calls, tool use, and more.
Home-page: https://github.com/sam33r/smai
Author: Sameer Ahuja
Author-email: mail@sameerahuja.com
Classifier: Programming Language :: Python :: 3
Classifier: License :: OSI Approved :: MIT License
Classifier: Operating System :: OS Independent
Requires-Python: >=3.7
License-File: LICENSE
Requires-Dist: requests
Requires-Dist: litellm
Requires-Dist: dataclasses
Requires-Dist: appdirs
Requires-Dist: pylibmagic
Requires-Dist: python-magic
Requires-Dist: keyring
Requires-Dist: click
Dynamic: author
Dynamic: author-email
Dynamic: classifier
Dynamic: description
Dynamic: description-content-type
Dynamic: home-page
Dynamic: license-file
Dynamic: requires-dist
Dynamic: requires-python
Dynamic: summary
